arches_orm/__init__.py
arches_orm/adapter.py
arches_orm/collection.py
arches_orm/datatypes.py
arches_orm/errors.py
arches_orm/hooks.py
arches_orm/models.py
arches_orm/utils.py
arches_orm/wkrm.py
arches_orm/wrapper.py
arches_orm/_internals/__init__.py
arches_orm/arches_django/__init__.py
arches_orm/arches_django/adapter.py
arches_orm/arches_django/apps.py
arches_orm/arches_django/bulk_create.py
arches_orm/arches_django/filters.py
arches_orm/arches_django/hooks.py
arches_orm/arches_django/middleware.py
arches_orm/arches_django/pseudo_nodes.py
arches_orm/arches_django/wrapper.py
arches_orm/arches_django/datatypes/__init__.py
arches_orm/arches_django/datatypes/_register.py
arches_orm/arches_django/datatypes/concepts.py
arches_orm/arches_django/datatypes/django_group.py
arches_orm/arches_django/datatypes/geojson_feature_collection.py
arches_orm/arches_django/datatypes/resource_instances.py
arches_orm/arches_django/datatypes/semantic.py
arches_orm/arches_django/datatypes/string.py
arches_orm/arches_django/datatypes/user.py
arches_orm/dummy/__init__.py
arches_orm/dummy/adapter.py
arches_orm/dummy/wrapper.py
arches_orm/graphql/__init__.py
arches_orm/graphql/_asgi.py
arches_orm/graphql/auth.py
arches_orm/graphql/concepts.py
arches_orm/graphql/django_asgi.py
arches_orm/graphql/resource_models.py
arches_orm/graphql/resources.py
arches_orm/graphql/utils.py
arches_orm/view_models/__init__.py
arches_orm/view_models/_base.py
arches_orm/view_models/concepts.py
arches_orm/view_models/geojson_feature_collection.py
arches_orm/view_models/group.py
arches_orm/view_models/node_list.py
arches_orm/view_models/resources.py
arches_orm/view_models/semantic.py
arches_orm/view_models/string.py
arches_orm/view_models/user.py
arches_orm-0.0.1.dist-info/LICENSE.txt
arches_orm-0.0.1.dist-info/METADATA
arches_orm-0.0.1.dist-info/WHEEL
arches_orm-0.0.1.dist-info/top_level.txt
arches_orm-0.0.1.dist-info/RECORD
