Metadata-Version: 2.1
Name: arches-orm
Version: 0.0.1
Summary: Experimental Arches Object Relational Mapper
Author-email: Phil Weir <phil.weir@flaxandteal.co.uk>
Classifier: Development Status :: 3 - Alpha
Classifier: License :: OSI Approved :: MIT License
Classifier: Natural Language :: English
Classifier: Operating System :: OS Independent
Classifier: Programming Language :: Python
Classifier: Programming Language :: Python :: 3.9
Classifier: Programming Language :: Python :: 3.10
Requires-Python: >=3.9
License-File: LICENSE.txt
Requires-Dist: tabulate
Requires-Dist: geojson
Provides-Extra: arches
Requires-Dist: arches ; extra == 'arches'
Provides-Extra: graphql
Requires-Dist: starlette ; extra == 'graphql'
Requires-Dist: starlette-context ; extra == 'graphql'
Requires-Dist: starlette-graphene3 ; extra == 'graphql'
Requires-Dist: oauth2-provider ; extra == 'graphql'
Requires-Dist: aiodataloader ; extra == 'graphql'
Requires-Dist: django-oauth2-provider ; extra == 'graphql'
Requires-Dist: graphene-file-upload ; extra == 'graphql'
Requires-Dist: graphene ; extra == 'graphql'
Requires-Dist: uvicorn[standard] ; extra == 'graphql'
Requires-Dist: aiohttp ; extra == 'graphql'
Provides-Extra: test
Requires-Dist: pytest ; extra == 'test'
Requires-Dist: httpx ; extra == 'test'
Requires-Dist: spatialite ; extra == 'test'
Requires-Dist: pytest-django ; extra == 'test'
Requires-Dist: arches-graphql-client ; extra == 'test'
Requires-Dist: pytest-asyncio ; extra == 'test'
